{
  "id": "cern-2020-revista-01",
  "eixo": "cern",
  "ano": 2020,
  "titulo": "Performance Evaluation of Energy Reconstruction Methods in High Energy Physics Experiments",
  "autores": "Juan Lieber Marin; Eduardo Furtado de Simas Filho; Bernardo Sotto-Maior Peralva; Guilherme Inácio Gonçalves; Luciano Manhães de Andrade Filho; José Manoel de Seixas",
  "tipo": "revista",
  "nivel": null,
  "arquivo": "/publications/pdfs/cern/2020/cern-revista-2020-juan-lieber-performance-energy-reconstruction.pdf",
  "veiculo": "Revista Mundi: Engenharia e Gestão, v. 5, n. 2 (2020)",
  "palavrasChave": [
    "high energy physics",
    "energy reconstruction",
    "calorimetry",
    "optimal filter",
    "multi-amplitude estimator",
    "pile-up"
  ],
  "resumo": "O artigo avalia a performance de dois métodos de reconstrução de energia em experimentos de física de altas energias: o Optimal Filter (OF) e o Multi-Amplitude Estimator (MAE). Utilizando dados simulados com diferentes níveis de empilhamento de sinais (pile-up), os autores demonstram que o método MAE apresenta desempenho superior ao OF em cenários de alta ocupação, embora seja sensível à calibração do pedestal.",
  "doi": "10.21575/25254782rmetg2020vol5n21169"
}
